{
  "project_info": {
    "project_number": "753656888733",
    "project_id": "authenticationsystem-6f8c2",
    "storage_bucket": "authenticationsystem-6f8c2.appspot.com"
  },
  "client": [
    {
      "client_info": {
        "mobilesdk_app_id": "1:753656888733:android:ee8bc899bc3b3e2f2f0374",
        "android_client_info": {
          "package_name": "com.example.authenticationsystem"
        }
      },
      "oauth_client": [],
      "api_key": [
        {
          "current_key": "AIzaSyAU3bq8PIQnU1v_nqHd_Oq-qv7tcdfbEac"
        }
      ],
      "services": {
        "appinvite_service": {
          "other_platform_oauth_client": []
        }
      }
    }
  ],
  "configuration_version": "1"
}